<?xml version="1.0" encoding="UTF-16"?>
<Task version="1.4" xmlns="http://schemas.microsoft.com/windows/2004/02/mit/task">
  <RegistrationInfo>
    <Date>2020-11-19T10:21:26.8424436</Date>
    <Author>Administrators</Author>
    <URI>\Get_AP3_Status-ST</URI>
  </RegistrationInfo>
  <Principals>
    <Principal id="Author">
      <GroupId>S-1-5-32-545</GroupId>
      <RunLevel>HighestAvailable</RunLevel>
    </Principal>
  </Principals>
  <Settings>
    <DisallowStartIfOnBatteries>false</DisallowStartIfOnBatteries>
    <StopIfGoingOnBatteries>true</StopIfGoingOnBatteries>
    <Enabled>false</Enabled>
    <Hidden>true</Hidden>
    <MultipleInstancesPolicy>IgnoreNew</MultipleInstancesPolicy>
    <IdleSettings>
      <StopOnIdleEnd>true</StopOnIdleEnd>
      <RestartOnIdle>false</RestartOnIdle>
    </IdleSettings>
    <UseUnifiedSchedulingEngine>true</UseUnifiedSchedulingEngine>
  </Settings>
  <Triggers />
  <Actions Context="Author">
    <Exec>
      <Command>powershell.exe</Command>
      <Arguments>-ExecutionPolicy Bypass -NoProfile -WindowStyle Hidden -File c:\temp\getAP3status.ps1</Arguments>
    </Exec>
  </Actions>
</Task>
